{
  "trackers": [],
  "cookies": [
    {
      "name": "__cf_bm",
      "value": "ZvlVTfsaOBl1qTKWLfSMyquND4QO.6R0v9DS3tmqv80-1742693839-1.0.1.1-R9A2o3c5W5VzFCYNnaebltnCx3lKVj508_IiYSUO6Qnz1ycvK4sWBJriKvmXrMjYRuRE7lBh3MrOU_vBI2JeLqcQYv.m8.LLz.ueYG9FjU0",
      "domain": ".mespoints.permisdeconduire.gouv.fr",
      "path": "/",
      "expires": 1742695639.047888,
      "size": 177,
      "httpOnly": true,
      "secure": true,
      "session": false,
      "sameSite": "None",
      "priority": "Medium",
      "sameParty": false,
      "sourceScheme": "Secure"
    }
  ],
  "headers": {
    "cache-control": "max-age=15",
    "cf-ray": "924a33ede887172b-IAD",
    "content-encoding": "gzip",
    "content-type": "text/html; charset=UTF-8",
    "date": "Sun, 23 Mar 2025 01:37:19 GMT",
    "expires": "Sun, 23 Mar 2025 01:37:34 GMT",
    "referrer-policy": "same-origin",
    "server": "cloudflare",
    "set-cookie": "__cf_bm=ZvlVTfsaOBl1qTKWLfSMyquND4QO.6R0v9DS3tmqv80-1742693839-1.0.1.1-R9A2o3c5W5VzFCYNnaebltnCx3lKVj508_IiYSUO6Qnz1ycvK4sWBJriKvmXrMjYRuRE7lBh3MrOU_vBI2JeLqcQYv.m8.LLz.ueYG9FjU0; path=/; expires=Sun, 23-Mar-25 02:07:19 GMT; domain=.mespoints.permisdeconduire.gouv.fr; HttpOnly; Secure; SameSite=None",
    "vary": "Accept-Encoding",
    "x-frame-options": "SAMEORIGIN"
  },
  "endpoints": [
    {
      "hostname": "mespoints.permisdeconduire.gouv.fr",
      "ip": "104.21.12.57",
      "geoip": {
        "registered_country": {
          "geoname_id": 6252001,
          "iso_code": "US",
          "names": {
            "de": "USA",
            "en": "United States",
            "es": "Estados Unidos",
            "fr": "États Unis",
            "ja": "アメリカ",
            "pt-BR": "EUA",
            "ru": "США",
            "zh-CN": "美国"
          }
        }
      }
    }
  ]
}
