{
  "trackers": [],
  "cookies": [
    {
      "name": "__cf_bm",
      "value": "hATTJB2uV5x8RtA8mHK_CtsnMVntIkB2YR9HnAE4rp4-1752769246-1.0.1.1-JONfCtSEhyJ0GRBTLmfb9JGBsoAd8Tx07iujrsI0FVFzjftZERDDkV7mVXLCclcYkb28T02Ejp0EQ1cSSez6vK0fIrXwg0rqgbCbXVK.IGk",
      "domain": ".mespoints.permisdeconduire.gouv.fr",
      "path": "/",
      "expires": 1752771046.563223,
      "size": 177,
      "httpOnly": true,
      "secure": true,
      "session": false,
      "sameSite": "None",
      "priority": "Medium",
      "sameParty": false,
      "sourceScheme": "Secure"
    }
  ],
  "headers": {
    "cache-control": "private, max-age=0, no-store, no-cache, must-revalidate, post-check=0, pre-check=0",
    "cf-ray": "960b118eebaab90a-IAD",
    "content-encoding": "gzip",
    "content-type": "text/html; charset=UTF-8",
    "date": "Thu, 17 Jul 2025 16:20:46 GMT",
    "expires": "Thu, 01 Jan 1970 00:00:01 GMT",
    "referrer-policy": "same-origin",
    "server": "cloudflare",
    "set-cookie": "__cf_bm=hATTJB2uV5x8RtA8mHK_CtsnMVntIkB2YR9HnAE4rp4-1752769246-1.0.1.1-JONfCtSEhyJ0GRBTLmfb9JGBsoAd8Tx07iujrsI0FVFzjftZERDDkV7mVXLCclcYkb28T02Ejp0EQ1cSSez6vK0fIrXwg0rqgbCbXVK.IGk; path=/; expires=Thu, 17-Jul-25 16:50:46 GMT; domain=.mespoints.permisdeconduire.gouv.fr; HttpOnly; Secure; SameSite=None",
    "vary": "Accept-Encoding",
    "x-frame-options": "SAMEORIGIN"
  },
  "endpoints": [
    {
      "hostname": "mespoints.permisdeconduire.gouv.fr",
      "ip": "104.21.12.57",
      "geoip": {
        "registered_country": {
          "geoname_id": 6252001,
          "iso_code": "US",
          "names": {
            "de": "USA",
            "en": "United States",
            "es": "Estados Unidos",
            "fr": "États Unis",
            "ja": "アメリカ",
            "pt-BR": "EUA",
            "ru": "США",
            "zh-CN": "美国"
          }
        }
      }
    }
  ]
}
