{"token":"ic1h","url":"https://www.service-public.fr/","alias":"","last_status":200,"uptime":100,"down":false,"down_since":null,"error":null,"period":3600,"apdex_t":1,"string_match":"","enabled":true,"published":false,"disabled_locations":["lan","mia","sin","tok","syd"],"recipients":["email:3904917424","email:4191065909"],"last_check_at":"2022-05-29T00:35:10Z","next_check_at":"2022-05-29T01:35:05Z","mute_until":null,"favicon_url":"https://www.service-public.fr/resources/v-0481a85732/web/img/favicon/favicon.ico","custom_headers":{},"http_verb":"GET/HEAD","http_body":"","ssl":{"tested_at":"2022-05-28T15:38:02Z","expires_at":"2022-08-15T13:43:08Z","valid":true,"error":null},"metrics":{"apdex":1,"timings":{"redirect":0,"namelookup":946,"connection":93,"handshake":289,"response":104,"total":1432}},"uptimeGrade":"A","apdexGrade":"A"}