{
  "scan": {
    "algorithmVersion": 4,
    "grade": "B",
    "error": null,
    "score": 75,
    "statusCode": 200,
    "testsFailed": 2,
    "testsPassed": 8,
    "testsQuantity": 10,
    "responseHeaders": {
      "date": "Sun, 15 Feb 2026 01:08:36 GMT",
      "content-type": "text/html;charset=UTF-8",
      "connection": "close",
      "vary": "Accept-Encoding",
      "cache-control": "max-age=0, s-maxage=28800, public",
      "expires": "Sat, 14 Feb 2026 23:35:59 GMT",
      "x-content-type-options": "nosniff",
      "x-xss-protection": "0",
      "x-frame-options": "SAMEORIGIN",
      "content-language": "fr-FR",
      "age": "5556",
      "set-cookie": [
        "SP_SESSION=Nzk1ODc3NmUtNWNkNy00MDE4LTgyYjgtZmQ3NjQ0ZjMzMjVk; Domain=service-public.gouv.fr; Path=/; Secure; HttpOnly; SameSite=Lax",
        "TS01ad993f=012a7f58e0e67b3ad4abb3977ea6977171d90fff027aff7855e61870521e04f155c3e0b0a413633702d86359d224f4e9127007d6e8; Path=/; Secure; HttpOnly",
        "TS015ce0c6=012a7f58e0122d8a2b041326fdc38b106437c2f2457aff7855e61870521e04f155c3e0b0a44a7ff9b9273a9c71a5480801b72e4bfcb554f468dd38dc8a576739eb3cc1652f; path=/; domain=service-public.gouv.fr; HttpOnly; Secure"
      ],
      "access-control-allow-origin": "https://lannuaire.service-public.gouv.fr",
      "access-control-allow-headers": "Origin, X-Requested-With, Content-Type, Accept, Authorization,  x-csrf-token",
      "access-control-allow-methods": "GET, POST, PUT, DELETE, OPTIONS",
      "access-control-allow-credentials": "true",
      "referrer-policy": "strict-origin-when-cross-origin",
      "permissions-policy": "accelerometer=(), ambient-light-sensor=(), autoplay=(), battery=(), camera=(), cross-origin-isolated=(), display-capture=(), document-domain=(), encrypted-media=(), execution-while-not-rendered=(), execution-while-out-of-viewport=(), fullscreen=*, geolocation=(self), gyroscope=(), keyboard-map=(), magnetometer=(), microphone=(), midi=(), navigation-override=(), payment=(), picture-in-picture=(), publickey-credentials-get=(), screen-wake-lock=(), sync-xhr=*, usb=(), xr-spatial-tracking=()",
      "strict-transport-security": "max-age=63072000; includeSubDomains; preload",
      "cross-origin-opener-policy": "same-origin-allow-popups",
      "cross-origin-resource-policy": "cross-origin",
      "cross-origin-embedder-policy": "unsafe-none",
      "content-security-policy": "default-src 'self' *.service-public.fr *.gouv.fr; script-src 'self' 'unsafe-inline' 'unsafe-eval' *.abtasty.com https://policevss.minint.chat https://gendarmerie-nationale.minint.chat *.gouv.fr *.service-public.fr; connect-src 'self' *.abtasty.com *.service-public.fr *.gouv.fr *.readspeaker.com; img-src 'self' data: *.service-public.fr *.gouv.fr; font-src 'self' data: *.service-public.fr *.gouv.fr; style-src 'self' 'unsafe-inline' *.service-public.fr *.gouv.fr; object-src 'none'; frame-src *.gouv.fr *.service-public.fr https://gendarmerie-nationale.minint.chat https://policevss.minint.chat https://dggn.my.site.com https://www.youtube.com https://www.dailymotion.com https://vimeo.com https://www.youtube-nocookie.com *.readspeaker.com; frame-ancestors 'self' https://www.service-public.gouv.fr https://entreprendre.service-public.gouv.fr",
      "transfer-encoding": "chunked"
    }
  },
  "tests": {
    "content-security-policy": {
      "expectation": "csp-implemented-with-no-unsafe",
      "pass": false,
      "result": "csp-implemented-with-unsafe-inline",
      "scoreModifier": -20,
      "data": {
        "default-src": [
          "'self'",
          "*.gouv.fr",
          "*.service-public.fr"
        ],
        "script-src": [
          "'self'",
          "'unsafe-eval'",
          "'unsafe-inline'",
          "*.abtasty.com",
          "*.gouv.fr",
          "*.service-public.fr",
          "https://gendarmerie-nationale.minint.chat",
          "https://policevss.minint.chat"
        ],
        "connect-src": [
          "'self'",
          "*.abtasty.com",
          "*.gouv.fr",
          "*.readspeaker.com",
          "*.service-public.fr"
        ],
        "img-src": [
          "'self'",
          "*.gouv.fr",
          "*.service-public.fr",
          "data:"
        ],
        "font-src": [
          "'self'",
          "*.gouv.fr",
          "*.service-public.fr",
          "data:"
        ],
        "style-src": [
          "'self'",
          "'unsafe-inline'",
          "*.gouv.fr",
          "*.service-public.fr"
        ],
        "object-src": [
          "'none'"
        ],
        "frame-src": [
          "*.gouv.fr",
          "*.readspeaker.com",
          "*.service-public.fr",
          "https://dggn.my.site.com",
          "https://gendarmerie-nationale.minint.chat",
          "https://policevss.minint.chat",
          "https://vimeo.com",
          "https://www.dailymotion.com",
          "https://www.youtube-nocookie.com",
          "https://www.youtube.com"
        ],
        "frame-ancestors": [
          "'self'",
          "https://entreprendre.service-public.gouv.fr",
          "https://www.service-public.gouv.fr"
        ]
      },
      "http": true,
      "meta": false,
      "policy": {
        "antiClickjacking": true,
        "defaultNone": false,
        "insecureBaseUri": true,
        "insecureFormAction": true,
        "insecureSchemeActive": false,
        "insecureSchemePassive": false,
        "strictDynamic": false,
        "unsafeEval": true,
        "unsafeInline": true,
        "unsafeInlineStyle": true,
        "unsafeObjects": false
      },
      "numPolicies": 1
    },
    "cookies": {
      "expectation": "cookies-secure-with-httponly-sessions",
      "pass": true,
      "result": "cookies-secure-with-httponly-sessions",
      "scoreModifier": 0,
      "data": {
        "TS012e9d3d": {
          "domain": "www.service-public.fr",
          "httponly": true,
          "path": "/",
          "port": null,
          "secure": true
        },
        "SP_SESSION": {
          "domain": "service-public.gouv.fr",
          "httponly": true,
          "path": "/",
          "port": null,
          "samesite": "lax",
          "secure": true
        },
        "TS01ad993f": {
          "domain": "www.service-public.gouv.fr",
          "httponly": true,
          "path": "/",
          "port": null,
          "secure": true
        },
        "TS015ce0c6": {
          "domain": "service-public.gouv.fr",
          "httponly": true,
          "path": "/",
          "port": null,
          "secure": true
        }
      },
      "sameSite": false
    },
    "cross-origin-resource-sharing": {
      "expectation": "cross-origin-resource-sharing-not-implemented",
      "pass": true,
      "result": "cross-origin-resource-sharing-not-implemented",
      "scoreModifier": 0,
      "data": null
    },
    "redirection": {
      "expectation": "redirection-to-https",
      "pass": true,
      "result": "redirection-not-needed-no-http",
      "scoreModifier": 0,
      "destination": null,
      "redirects": true,
      "route": [],
      "statusCode": null
    },
    "referrer-policy": {
      "expectation": "referrer-policy-private",
      "pass": true,
      "result": "referrer-policy-private",
      "scoreModifier": 5,
      "data": "strict-origin-when-cross-origin",
      "http": true,
      "meta": false
    },
    "strict-transport-security": {
      "expectation": "hsts-implemented-max-age-at-least-six-months",
      "pass": true,
      "result": "hsts-implemented-max-age-at-least-six-months",
      "scoreModifier": 0,
      "data": "max-age=63072000; includeSubDomains; preload",
      "includeSubDomains": true,
      "maxAge": 63072000,
      "preload": true,
      "preloaded": false
    },
    "subresource-integrity": {
      "expectation": "sri-implemented-and-external-scripts-loaded-securely",
      "pass": false,
      "result": "sri-not-implemented-but-external-scripts-loaded-securely",
      "scoreModifier": -5,
      "data": {
        "https://try.abtasty.com/f2a27ecc441fb1662a47bee9ea97d2ea.js": {
          "crossorigin": null,
          "integrity": null
        },
        "https://www.service-public.gouv.fr/resources/v-b00b8c5f60/assets/js/readspeaker/webReader.js?pids=wr&notools=1": {
          "crossorigin": "anonymous",
          "integrity": "sha384-lzKF3q93rwr6Dkx85dTWD73+IApvfO/ZfAeThrWcxQW6VdVUlHXEEv3kVyK04oYp"
        },
        "https://www.service-public.gouv.fr/resources/v-b00b8c5f60/assets/dsfr-1.14/dist/dsfr.module.min.js": {
          "crossorigin": null,
          "integrity": null
        },
        "https://www.service-public.gouv.fr/resources/v-b00b8c5f60/assets/dsfr-1.14/dist/dsfr.nomodule.min.js": {
          "crossorigin": null,
          "integrity": null
        },
        "https://www.service-public.gouv.fr/resources/v-b00b8c5f60/assets/dsfr-1.14/dist/analytics/analytics.module.min.js": {
          "crossorigin": null,
          "integrity": null
        },
        "https://www.service-public.gouv.fr/resources/v-b00b8c5f60/assets/dsfr-1.14/dist/analytics/analytics.nomodule.min.js": {
          "crossorigin": null,
          "integrity": null
        },
        "https://www.service-public.gouv.fr/resources/v-b00b8c5f60/assets/js/require.js": {
          "crossorigin": null,
          "integrity": null
        },
        "https://www.service-public.gouv.fr/resources/v-b00b8c5f60/assets/js/common.js": {
          "crossorigin": null,
          "integrity": null
        },
        "https://www.service-public.gouv.fr/resources/v-b00b8c5f60/assets/dsfr-1.14/js/configRgpdPart.js": {
          "crossorigin": null,
          "integrity": null
        },
        "https://www.service-public.gouv.fr/resources/v-b00b8c5f60/assets/js/coperia.js": {
          "crossorigin": null,
          "integrity": null
        }
      }
    },
    "x-content-type-options": {
      "expectation": "x-content-type-options-nosniff",
      "pass": true,
      "result": "x-content-type-options-nosniff",
      "scoreModifier": 0,
      "data": "nosniff"
    },
    "x-frame-options": {
      "expectation": "x-frame-options-sameorigin-or-deny",
      "pass": true,
      "result": "x-frame-options-implemented-via-csp",
      "scoreModifier": 5,
      "data": "SAMEORIGIN"
    },
    "cross-origin-resource-policy": {
      "expectation": "corp-implemented-with-same-site",
      "pass": true,
      "result": "corp-implemented-with-cross-origin",
      "scoreModifier": 0,
      "data": "cross-origin",
      "http": true,
      "meta": false
    }
  }
}
