{
  "trackers": [
    {
      "type": "jsdelivr",
      "url": "https://cdn.jsdelivr.net/npm/remixicon@2.2.0/fonts/remixicon.css",
      "details": {
        "id": "jsdelivr",
        "message": "Host files locally"
      }
    },
    {
      "type": "unknown",
      "url": "https://cdn.printfriendly.com/printfriendly.js"
    },
    {
      "type": "unknown",
      "url": "https://www.printfriendly.com/api/v3/domain_settings/a?callback=pfMod.saveDSSettings&hostname=www.interieur.gouv.fr&client_version=client"
    }
  ],
  "cookies": [
    {
      "name": "tarteaucitron",
      "value": "!adform=wait!eulerian=wait!twitter=wait!twitterembed=wait!twittertimeline=wait!ausha=wait!dailymotion=wait!vimeo=wait!youtube=wait",
      "domain": "www.interieur.gouv.fr",
      "path": "/",
      "expires": 1725842716,
      "size": 143,
      "httpOnly": false,
      "secure": true,
      "session": false,
      "sameSite": "Lax",
      "sameParty": false,
      "sourceScheme": "Secure",
      "sourcePort": 443
    }
  ],
  "headers": {
    "accept-ranges": "bytes",
    "age": "1897",
    "cache-control": "max-age=3600, public",
    "cache-tags": "MISS",
    "content-encoding": "gzip",
    "content-language": "fr",
    "content-length": "12710",
    "content-type": "text/html; charset=UTF-8",
    "date": "Sun, 10 Sep 2023 00:45:14 GMT",
    "ec_policy_version": "V4.7b",
    "etag": "\"1694281191\"",
    "expires": "Sun, 19 Nov 1978 05:00:00 GMT",
    "last-modified": "Sat, 09 Sep 2023 17:39:51 GMT",
    "server": "ECAcc (saa/83DD)",
    "strict-transport-security": "max-age=63072000; includeSubdomains\nmax-age=31536000; includeSubdomains\nmax-age=63072000; includeSubdomains",
    "vary": "Accept-Encoding",
    "x-cache": "HIT",
    "x-cache-hits": "0",
    "x-cdn": "Imperva",
    "x-content-type-options": "nosniff",
    "x-drupal-dynamic-cache": "UNCACHEABLE",
    "x-frame-options": "SAMEORIGIN",
    "x-iinfo": "14-10483571-10477173 pNYy RT(1694304816747 152) q(0 1 1 -1) r(1 1) U24",
    "x-ua-compatible": "IE=edge"
  },
  "endpoints": [
    {
      "hostname": "www.interieur.gouv.fr",
      "ip": "152.199.5.204",
      "geoip": {
        "continent": {
          "code": "NA",
          "geoname_id": 6255149,
          "names": {
            "de": "Nordamerika",
            "en": "North America",
            "es": "Norteamérica",
            "fr": "Amérique du Nord",
            "ja": "北アメリカ",
            "pt-BR": "América do Norte",
            "ru": "Северная Америка",
            "zh-CN": "北美洲"
          }
        },
        "country": {
          "geoname_id": 6252001,
          "iso_code": "US",
          "names": {
            "de": "Vereinigte Staaten",
            "en": "United States",
            "es": "Estados Unidos",
            "fr": "États Unis",
            "ja": "アメリカ",
            "pt-BR": "EUA",
            "ru": "США",
            "zh-CN": "美国"
          }
        },
        "location": {
          "accuracy_radius": 1000,
          "latitude": 37.751,
          "longitude": -97.822,
          "time_zone": "America/Chicago"
        },
        "registered_country": {
          "geoname_id": 6252001,
          "iso_code": "US",
          "names": {
            "de": "Vereinigte Staaten",
            "en": "United States",
            "es": "Estados Unidos",
            "fr": "États Unis",
            "ja": "アメリカ",
            "pt-BR": "EUA",
            "ru": "США",
            "zh-CN": "美国"
          }
        }
      }
    },
    {
      "hostname": "cdn.jsdelivr.net",
      "ip": "151.101.201.229",
      "geoip": {
        "city": {
          "geoname_id": 5393015,
          "names": {
            "de": "Santa Clara",
            "en": "Santa Clara",
            "es": "Santa Clara",
            "fr": "Santa Clara",
            "ja": "サンタクララ",
            "pt-BR": "Santa Clara",
            "ru": "Санта-Клара",
            "zh-CN": "圣克拉拉"
          }
        },
        "continent": {
          "code": "NA",
          "geoname_id": 6255149,
          "names": {
            "de": "Nordamerika",
            "en": "North America",
            "es": "Norteamérica",
            "fr": "Amérique du Nord",
            "ja": "北アメリカ",
            "pt-BR": "América do Norte",
            "ru": "Северная Америка",
            "zh-CN": "北美洲"
          }
        },
        "country": {
          "geoname_id": 6252001,
          "iso_code": "US",
          "names": {
            "de": "Vereinigte Staaten",
            "en": "United States",
            "es": "Estados Unidos",
            "fr": "États Unis",
            "ja": "アメリカ",
            "pt-BR": "EUA",
            "ru": "США",
            "zh-CN": "美国"
          }
        },
        "location": {
          "accuracy_radius": 20,
          "latitude": 37.3931,
          "longitude": -121.962,
          "metro_code": 807,
          "time_zone": "America/Los_Angeles"
        },
        "postal": {
          "code": "95054"
        },
        "registered_country": {
          "geoname_id": 6252001,
          "iso_code": "US",
          "names": {
            "de": "Vereinigte Staaten",
            "en": "United States",
            "es": "Estados Unidos",
            "fr": "États Unis",
            "ja": "アメリカ",
            "pt-BR": "EUA",
            "ru": "США",
            "zh-CN": "美国"
          }
        },
        "subdivisions": [
          {
            "geoname_id": 5332921,
            "iso_code": "CA",
            "names": {
              "de": "Kalifornien",
              "en": "California",
              "es": "California",
              "fr": "Californie",
              "ja": "カリフォルニア州",
              "pt-BR": "Califórnia",
              "ru": "Калифорния",
              "zh-CN": "加州"
            }
          }
        ]
      }
    },
    {
      "hostname": "cdn.printfriendly.com",
      "ip": "169.150.221.147",
      "geoip": {
        "city": {
          "geoname_id": 5392171,
          "names": {
            "de": "San José",
            "en": "San Jose",
            "es": "San José",
            "fr": "San José",
            "ja": "サンノゼ",
            "pt-BR": "San José",
            "ru": "Сан-Хосе"
          }
        },
        "continent": {
          "code": "NA",
          "geoname_id": 6255149,
          "names": {
            "de": "Nordamerika",
            "en": "North America",
            "es": "Norteamérica",
            "fr": "Amérique du Nord",
            "ja": "北アメリカ",
            "pt-BR": "América do Norte",
            "ru": "Северная Америка",
            "zh-CN": "北美洲"
          }
        },
        "country": {
          "geoname_id": 6252001,
          "iso_code": "US",
          "names": {
            "de": "Vereinigte Staaten",
            "en": "United States",
            "es": "Estados Unidos",
            "fr": "États Unis",
            "ja": "アメリカ",
            "pt-BR": "EUA",
            "ru": "США",
            "zh-CN": "美国"
          }
        },
        "location": {
          "accuracy_radius": 20,
          "latitude": 37.1835,
          "longitude": -121.7714,
          "metro_code": 807,
          "time_zone": "America/Los_Angeles"
        },
        "postal": {
          "code": "95141"
        },
        "registered_country": {
          "geoname_id": 2635167,
          "iso_code": "GB",
          "names": {
            "de": "Vereinigtes Königreich",
            "en": "United Kingdom",
            "es": "Reino Unido",
            "fr": "Royaume Uni",
            "ja": "英国",
            "pt-BR": "Reino Unido",
            "ru": "Британия",
            "zh-CN": "英国"
          }
        },
        "subdivisions": [
          {
            "geoname_id": 5332921,
            "iso_code": "CA",
            "names": {
              "de": "Kalifornien",
              "en": "California",
              "es": "California",
              "fr": "Californie",
              "ja": "カリフォルニア州",
              "pt-BR": "Califórnia",
              "ru": "Калифорния",
              "zh-CN": "加州"
            }
          }
        ]
      }
    },
    {
      "hostname": "www.printfriendly.com",
      "ip": "34.122.247.123",
      "geoip": {
        "city": {
          "geoname_id": 4852832,
          "names": {
            "en": "Council Bluffs",
            "ja": "カウンシルブラフス",
            "ru": "Каунсил-Блафс",
            "zh-CN": "康瑟尔布拉夫斯"
          }
        },
        "continent": {
          "code": "NA",
          "geoname_id": 6255149,
          "names": {
            "de": "Nordamerika",
            "en": "North America",
            "es": "Norteamérica",
            "fr": "Amérique du Nord",
            "ja": "北アメリカ",
            "pt-BR": "América do Norte",
            "ru": "Северная Америка",
            "zh-CN": "北美洲"
          }
        },
        "country": {
          "geoname_id": 6252001,
          "iso_code": "US",
          "names": {
            "de": "Vereinigte Staaten",
            "en": "United States",
            "es": "Estados Unidos",
            "fr": "États Unis",
            "ja": "アメリカ",
            "pt-BR": "EUA",
            "ru": "США",
            "zh-CN": "美国"
          }
        },
        "location": {
          "accuracy_radius": 1000,
          "latitude": 41.2591,
          "longitude": -95.8517,
          "metro_code": 652,
          "time_zone": "America/Chicago"
        },
        "postal": {
          "code": "51502"
        },
        "registered_country": {
          "geoname_id": 6252001,
          "iso_code": "US",
          "names": {
            "de": "Vereinigte Staaten",
            "en": "United States",
            "es": "Estados Unidos",
            "fr": "États Unis",
            "ja": "アメリカ",
            "pt-BR": "EUA",
            "ru": "США",
            "zh-CN": "美国"
          }
        },
        "subdivisions": [
          {
            "geoname_id": 4862182,
            "iso_code": "IA",
            "names": {
              "de": "Iowa",
              "en": "Iowa",
              "es": "Iowa",
              "fr": "Iowa",
              "ja": "アイオワ州",
              "pt-BR": "Iova",
              "ru": "Айова",
              "zh-CN": "艾奥瓦州"
            }
          }
        ]
      }
    }
  ]
}
