{
  "trackers": [
    {
      "type": "jsdelivr",
      "url": "https://cdn.jsdelivr.net/npm/remixicon@2.2.0/fonts/remixicon.css",
      "details": {
        "id": "jsdelivr",
        "message": "Host files locally"
      }
    }
  ],
  "cookies": [
    {
      "name": "tarteaucitron",
      "value": "!adform=wait!eulerian=wait!twitter=wait!twitterembed=wait!twittertimeline=wait!ausha=wait!dailymotion=wait!vimeo=wait!youtube=wait",
      "domain": "www.interieur.gouv.fr",
      "path": "/",
      "expires": 1737334179,
      "size": 143,
      "httpOnly": false,
      "secure": true,
      "session": false,
      "sameSite": "Lax",
      "sameParty": false,
      "sourceScheme": "Secure",
      "sourcePort": 443
    }
  ],
  "headers": {
    "accept-ranges": "bytes",
    "age": "2094",
    "cache-control": "no-cache, no-store, must-revalidate",
    "cache-tags": "MISS",
    "content-encoding": "gzip",
    "content-language": "fr",
    "content-length": "11856",
    "content-type": "text/html; charset=UTF-8",
    "date": "Sun, 21 Jan 2024 00:49:38 GMT",
    "ec_policy_version": "V5.1",
    "etag": "\"1705681309\"",
    "expires": "Sun, 19 Nov 1978 05:00:00 GMT",
    "last-modified": "Fri, 19 Jan 2024 16:21:49 GMT",
    "server": "ECAcc (sac/2533)",
    "strict-transport-security": "max-age=63072000; includeSubdomains\nmax-age=31536000; includeSubdomains\nmax-age=63072000; includeSubdomains",
    "vary": "Accept-Encoding",
    "x-cache": "HIT",
    "x-cache-hits": "0",
    "x-cdn": "Imperva",
    "x-content-type-options": "nosniff",
    "x-drupal-dynamic-cache": "UNCACHEABLE",
    "x-frame-options": "SAMEORIGIN",
    "x-iinfo": "5-15659147-15659162 NNNN CT(8 14 0) RT(1705796084533 156) q(0 0 1 -1) r(1 1) U24"
  },
  "endpoints": [
    {
      "hostname": "www.interieur.gouv.fr",
      "ip": "152.199.5.204",
      "geoip": {
        "continent": {
          "code": "NA",
          "geoname_id": 6255149,
          "names": {
            "de": "Nordamerika",
            "en": "North America",
            "es": "Norteamérica",
            "fr": "Amérique du Nord",
            "ja": "北アメリカ",
            "pt-BR": "América do Norte",
            "ru": "Северная Америка",
            "zh-CN": "北美洲"
          }
        },
        "country": {
          "geoname_id": 6252001,
          "iso_code": "US",
          "names": {
            "de": "USA",
            "en": "United States",
            "es": "Estados Unidos",
            "fr": "États Unis",
            "ja": "アメリカ",
            "pt-BR": "EUA",
            "ru": "США",
            "zh-CN": "美国"
          }
        },
        "location": {
          "accuracy_radius": 1000,
          "latitude": 37.751,
          "longitude": -97.822,
          "time_zone": "America/Chicago"
        },
        "registered_country": {
          "geoname_id": 6252001,
          "iso_code": "US",
          "names": {
            "de": "USA",
            "en": "United States",
            "es": "Estados Unidos",
            "fr": "États Unis",
            "ja": "アメリカ",
            "pt-BR": "EUA",
            "ru": "США",
            "zh-CN": "美国"
          }
        }
      }
    },
    {
      "hostname": "cdn.jsdelivr.net",
      "ip": "146.75.93.229",
      "geoip": {
        "city": {
          "geoname_id": 5368361,
          "names": {
            "de": "Los Angeles",
            "en": "Los Angeles",
            "es": "Los Ángeles",
            "fr": "Los Angeles",
            "ja": "ロサンゼルス",
            "pt-BR": "Los Angeles",
            "ru": "Лос-Анджелес",
            "zh-CN": "洛杉矶"
          }
        },
        "continent": {
          "code": "NA",
          "geoname_id": 6255149,
          "names": {
            "de": "Nordamerika",
            "en": "North America",
            "es": "Norteamérica",
            "fr": "Amérique du Nord",
            "ja": "北アメリカ",
            "pt-BR": "América do Norte",
            "ru": "Северная Америка",
            "zh-CN": "北美洲"
          }
        },
        "country": {
          "geoname_id": 6252001,
          "iso_code": "US",
          "names": {
            "de": "USA",
            "en": "United States",
            "es": "Estados Unidos",
            "fr": "États Unis",
            "ja": "アメリカ",
            "pt-BR": "EUA",
            "ru": "США",
            "zh-CN": "美国"
          }
        },
        "location": {
          "accuracy_radius": 20,
          "latitude": 34.0544,
          "longitude": -118.244,
          "metro_code": 803,
          "time_zone": "America/Los_Angeles"
        },
        "postal": {
          "code": "90012"
        },
        "registered_country": {
          "geoname_id": 6252001,
          "iso_code": "US",
          "names": {
            "de": "USA",
            "en": "United States",
            "es": "Estados Unidos",
            "fr": "États Unis",
            "ja": "アメリカ",
            "pt-BR": "EUA",
            "ru": "США",
            "zh-CN": "美国"
          }
        },
        "subdivisions": [
          {
            "geoname_id": 5332921,
            "iso_code": "CA",
            "names": {
              "de": "Kalifornien",
              "en": "California",
              "es": "California",
              "fr": "Californie",
              "ja": "カリフォルニア州",
              "pt-BR": "Califórnia",
              "ru": "Калифорния",
              "zh-CN": "加州"
            }
          }
        ]
      }
    }
  ]
}
