{
  "trackers": [],
  "cookies": [
    {
      "name": "__cf_bm",
      "value": "z55CvS5SAYC697KlRr0.HXtiXdyOQeC_wEqxmO_EyrY-1757785828-1.0.1.1-j1WV6s21KV7.HFVoFdbyIBcT5enp9w8oaZbTHWi9Yj5qnqRKtOPzkxNqyU12krBKyDHjwRQiQ7X6Uy6nIv_ULDWqMTRkjdHpuPiqxTsLDdE",
      "domain": ".permisdeconduire.gouv.fr",
      "path": "/",
      "expires": 1757787628.414969,
      "size": 177,
      "httpOnly": true,
      "secure": true,
      "session": false,
      "sameSite": "None",
      "priority": "Medium",
      "sameParty": false,
      "sourceScheme": "Secure"
    }
  ],
  "headers": {
    "cache-control": "private, max-age=0, no-store, no-cache, must-revalidate, post-check=0, pre-check=0",
    "cf-ray": "97e97cb328e22e2d-DFW",
    "content-encoding": "gzip",
    "content-type": "text/html; charset=UTF-8",
    "date": "Sat, 13 Sep 2025 17:50:28 GMT",
    "expires": "Thu, 01 Jan 1970 00:00:01 GMT",
    "referrer-policy": "same-origin",
    "server": "cloudflare",
    "set-cookie": "__cf_bm=z55CvS5SAYC697KlRr0.HXtiXdyOQeC_wEqxmO_EyrY-1757785828-1.0.1.1-j1WV6s21KV7.HFVoFdbyIBcT5enp9w8oaZbTHWi9Yj5qnqRKtOPzkxNqyU12krBKyDHjwRQiQ7X6Uy6nIv_ULDWqMTRkjdHpuPiqxTsLDdE; path=/; expires=Sat, 13-Sep-25 18:20:28 GMT; domain=.permisdeconduire.gouv.fr; HttpOnly; Secure; SameSite=None",
    "vary": "Accept-Encoding",
    "x-frame-options": "SAMEORIGIN"
  },
  "endpoints": [
    {
      "hostname": "pro.permisdeconduire.gouv.fr",
      "ip": "104.18.6.65",
      "geoip": {
        "registered_country": {
          "geoname_id": 6252001,
          "iso_code": "US",
          "names": {
            "de": "USA",
            "en": "United States",
            "es": "Estados Unidos",
            "fr": "États Unis",
            "ja": "アメリカ",
            "pt-BR": "EUA",
            "ru": "США",
            "zh-CN": "美国"
          }
        }
      }
    }
  ]
}
